pgmenu/GlobalFunctions.py
pgmenu/README.md
pgmenu/VarelaRound.ttf
pgmenu/__init__.py
pgmenu/button.py
pgmenu/checkbox.py
pgmenu/frame.py
pgmenu/image.py
pgmenu/main.py
pgmenu/menu.py
pgmenu/text.py
pgmenu/textbox.py
pgmenu/theme.py
pgmenu-1.5.1.dist-info/METADATA
pgmenu-1.5.1.dist-info/WHEEL
pgmenu-1.5.1.dist-info/top_level.txt
pgmenu-1.5.1.dist-info/RECORD
