Metadata-Version: 2.1
Name: pgmenu
Version: 1.5.1
Summary: A pygame menu library
Home-page: https://github.com/Vermylion/pgmenu
Author: Vermylion
Author-email: vermylioncode@gmail.com
Project-URL: Bug Tracker, https://github.com/Vermylion/pgmenu
Classifier: Programming Language :: Python :: 3
Classifier: License :: OSI Approved :: MIT License
Classifier: Operating System :: OS Independent
Requires-Python: >=3.7
Requires-Dist: pygame
Requires-Dist: Pillow
Requires-Dist: darkdetect
